README.md
setup.py
src/data/__init__.py
src/data/make_dataset.py
src/features/__init__.py
src/features/build_features.py
src/haemapy/__init__.py
src/haemapy/cli.py
src/haemapy/banner/__init__.py
src/haemapy/banner/cli.py
src/haemapy/banner/http.py
src/haemapy/banner/model.py
src/haemapy/http/__init__.py
src/haemapy/http/server.py
src/hematopy.egg-info/PKG-INFO
src/hematopy.egg-info/SOURCES.txt
src/hematopy.egg-info/dependency_links.txt
src/hematopy.egg-info/entry_points.txt
src/hematopy.egg-info/requires.txt
src/hematopy.egg-info/top_level.txt
src/models/__init__.py
src/models/predict_model.py
src/models/train_model.py
src/visualization/__init__.py
src/visualization/visualize.py