Metadata-Version: 1.2
Name: hematopy
Version: 0.0.1.dev6
Summary: Python and Blood
Home-page: UNKNOWN
Author: Gustavo RPS @ ArgoCrew/ArgoPy
Author-email: gustavorps+hematopy@argocrew.io
License: BSD-3
Project-URL: Issues, https://github.com/ArgoCrew/hematopy/issues
Project-URL: Source Code, https://github.com/ArgoCrew/hematopy
Keywords: blood banner utility
Platform: UNKNOWN
Classifier: Development Status :: 3 - Alpha
Classifier: Programming Language :: Python :: 3
Classifier: License :: OSI Approved :: BSD License
Classifier: Operating System :: OS Independent
Classifier: Topic :: Scientific/Engineering :: Medical Science Apps.
Classifier: Intended Audience :: Healthcare Industry
